{
  "project_info": {
    "project_number": "427990820745",
    "project_id": "flutter-learning-464c6",
    "storage_bucket": "flutter-learning-464c6.appspot.com"
  },
  "client": [
    {
      "client_info": {
        "mobilesdk_app_id": "1:427990820745:android:6a3b72aaa5c2d0d0aa6358",
        "android_client_info": {
          "package_name": "shopping.app.provider"
        }
      },
      "oauth_client": [],
      "api_key": [
        {
          "current_key": "AIzaSyBSvl8NCkt-Jl1g04MviO5BsOMuxU72efk"
        }
      ],
      "services": {
        "appinvite_service": {
          "other_platform_oauth_client": []
        }
      }
    }
  ],
  "configuration_version": "1"
}